AUTHORS
CHANGELOG.txt
DESCRIPTION
LICENSE
MANIFEST.in
setup.py
django_download_stats.egg-info/PKG-INFO
django_download_stats.egg-info/SOURCES.txt
django_download_stats.egg-info/dependency_links.txt
django_download_stats.egg-info/requires.txt
django_download_stats.egg-info/top_level.txt
download_stats/__init__.py
download_stats/admin.py
download_stats/context_processors.py
download_stats/models.py
download_stats/settings.py
download_stats/urls.py
download_stats/views.py
download_stats/migrations/0001_initial.py
download_stats/migrations/__init__.py
download_stats/templates/dummy_home.html
download_stats/tests/__init__.py
download_stats/tests/context_processors_tests.py
download_stats/tests/factories.py
download_stats/tests/models_tests.py
download_stats/tests/runtests.py
download_stats/tests/south_settings.py
download_stats/tests/test_settings.py
download_stats/tests/urls.py
download_stats/tests/integration_tests/views_tests.py