Metadata-Version: 1.0
Name: django-download-stats
Version: 0.2
Summary: A reusable Django app to track download statistis.
